<?xml version="1.0" encoding="UTF-8"?>
<!DOCTYPE mapper PUBLIC "-//mybatis.org//DTD Mapper 3.0//EN" "http://mybatis.org/dtd/mybatis-3-mapper.dtd">
<mapper namespace="com.t.zero.b.i.pump.db.dao.auto.UnitsMapper">
  <resultMap id="BaseResultMap" type="com.t.zero.b.i.pump.db.model.auto.Units">
    <!--
      WARNING - @mbg.generated
      This element is automatically generated by MyBatis Generator, do not modify.
      This element was generated on Fri Feb 24 16:09:40 CST 2023.
    -->
    <id column="id" jdbcType="INTEGER" property="id" />
    <result column="ProjectNumber" jdbcType="VARCHAR" property="projectnumber" />
    <result column="Q" jdbcType="VARCHAR" property="q" />
    <result column="H" jdbcType="VARCHAR" property="h" />
    <result column="Temp" jdbcType="VARCHAR" property="temp" />
    <result column="viscosity" jdbcType="VARCHAR" property="viscosity" />
    <result column="InnerPressure" jdbcType="VARCHAR" property="innerpressure" />
    <result column="OutPressure" jdbcType="VARCHAR" property="outpressure" />
    <result column="Gas" jdbcType="VARCHAR" property="gas" />
    <result column="Depth" jdbcType="VARCHAR" property="depth" />
    <result column="NPSHa" jdbcType="VARCHAR" property="npsha" />
    <result column="NPSHr" jdbcType="VARCHAR" property="npshr" />
    <result column="power_this" jdbcType="VARCHAR" property="powerThis" />
    <result column="level_moter" jdbcType="VARCHAR" property="levelMoter" />
    <result column="frequency" jdbcType="VARCHAR" property="frequency" />
  </resultMap>
  <sql id="Example_Where_Clause">
    <!--
      WARNING - @mbg.generated
      This element is automatically generated by MyBatis Generator, do not modify.
      This element was generated on Fri Feb 24 16:09:40 CST 2023.
    -->
    <where>
      <foreach collection="oredCriteria" item="criteria" separator="or">
        <if test="criteria.valid">
          <trim prefix="(" prefixOverrides="and" suffix=")">
            <foreach collection="criteria.criteria" item="criterion">
              <choose>
                <when test="criterion.noValue">
                  and ${criterion.condition}
                </when>
                <when test="criterion.singleValue">
                  and ${criterion.condition} #{criterion.value}
                </when>
                <when test="criterion.betweenValue">
                  and ${criterion.condition} #{criterion.value} and #{criterion.secondValue}
                </when>
                <when test="criterion.listValue">
                  and ${criterion.condition}
                  <foreach close=")" collection="criterion.value" item="listItem" open="(" separator=",">
                    #{listItem}
                  </foreach>
                </when>
              </choose>
            </foreach>
          </trim>
        </if>
      </foreach>
    </where>
  </sql>
  <sql id="Update_By_Example_Where_Clause">
    <!--
      WARNING - @mbg.generated
      This element is automatically generated by MyBatis Generator, do not modify.
      This element was generated on Fri Feb 24 16:09:40 CST 2023.
    -->
    <where>
      <foreach collection="example.oredCriteria" item="criteria" separator="or">
        <if test="criteria.valid">
          <trim prefix="(" prefixOverrides="and" suffix=")">
            <foreach collection="criteria.criteria" item="criterion">
              <choose>
                <when test="criterion.noValue">
                  and ${criterion.condition}
                </when>
                <when test="criterion.singleValue">
                  and ${criterion.condition} #{criterion.value}
                </when>
                <when test="criterion.betweenValue">
                  and ${criterion.condition} #{criterion.value} and #{criterion.secondValue}
                </when>
                <when test="criterion.listValue">
                  and ${criterion.condition}
                  <foreach close=")" collection="criterion.value" item="listItem" open="(" separator=",">
                    #{listItem}
                  </foreach>
                </when>
              </choose>
            </foreach>
          </trim>
        </if>
      </foreach>
    </where>
  </sql>
  <sql id="Base_Column_List">
    <!--
      WARNING - @mbg.generated
      This element is automatically generated by MyBatis Generator, do not modify.
      This element was generated on Fri Feb 24 16:09:40 CST 2023.
    -->
    id, ProjectNumber, Q, H, Temp, viscosity, InnerPressure, OutPressure, Gas, Depth, 
    NPSHa, NPSHr, power_this, level_moter, frequency
  </sql>
  <select id="selectByExample" parameterType="com.t.zero.b.i.pump.db.model.auto.UnitsExample" resultMap="BaseResultMap">
    <!--
      WARNING - @mbg.generated
      This element is automatically generated by MyBatis Generator, do not modify.
      This element was generated on Fri Feb 24 16:09:40 CST 2023.
    -->
    select
    <if test="distinct">
      distinct
    </if>
    <include refid="Base_Column_List" />
    from units
    <if test="_parameter != null">
      <include refid="Example_Where_Clause" />
    </if>
    <if test="orderByClause != null">
      order by ${orderByClause}
    </if>
  </select>
  <select id="selectByPrimaryKey" parameterType="java.lang.Integer" resultMap="BaseResultMap">
    <!--
      WARNING - @mbg.generated
      This element is automatically generated by MyBatis Generator, do not modify.
      This element was generated on Fri Feb 24 16:09:40 CST 2023.
    -->
    select 
    <include refid="Base_Column_List" />
    from units
    where id = #{id,jdbcType=INTEGER}
  </select>
  <delete id="deleteByPrimaryKey" parameterType="java.lang.Integer">
    <!--
      WARNING - @mbg.generated
      This element is automatically generated by MyBatis Generator, do not modify.
      This element was generated on Fri Feb 24 16:09:40 CST 2023.
    -->
    delete from units
    where id = #{id,jdbcType=INTEGER}
  </delete>
  <delete id="deleteByExample" parameterType="com.t.zero.b.i.pump.db.model.auto.UnitsExample">
    <!--
      WARNING - @mbg.generated
      This element is automatically generated by MyBatis Generator, do not modify.
      This element was generated on Fri Feb 24 16:09:40 CST 2023.
    -->
    delete from units
    <if test="_parameter != null">
      <include refid="Example_Where_Clause" />
    </if>
  </delete>
  <insert id="insert" parameterType="com.t.zero.b.i.pump.db.model.auto.Units">
    <!--
      WARNING - @mbg.generated
      This element is automatically generated by MyBatis Generator, do not modify.
      This element was generated on Fri Feb 24 16:09:40 CST 2023.
    -->
    <selectKey keyProperty="id" order="AFTER" resultType="java.lang.Integer">
      SELECT LAST_INSERT_ID()
    </selectKey>
    insert into units (ProjectNumber, Q, H, 
      Temp, viscosity, InnerPressure, 
      OutPressure, Gas, Depth, 
      NPSHa, NPSHr, power_this, 
      level_moter, frequency)
    values (#{projectnumber,jdbcType=VARCHAR}, #{q,jdbcType=VARCHAR}, #{h,jdbcType=VARCHAR}, 
      #{temp,jdbcType=VARCHAR}, #{viscosity,jdbcType=VARCHAR}, #{innerpressure,jdbcType=VARCHAR}, 
      #{outpressure,jdbcType=VARCHAR}, #{gas,jdbcType=VARCHAR}, #{depth,jdbcType=VARCHAR}, 
      #{npsha,jdbcType=VARCHAR}, #{npshr,jdbcType=VARCHAR}, #{powerThis,jdbcType=VARCHAR}, 
      #{levelMoter,jdbcType=VARCHAR}, #{frequency,jdbcType=VARCHAR})
  </insert>
  <insert id="insertSelective" parameterType="com.t.zero.b.i.pump.db.model.auto.Units">
    <!--
      WARNING - @mbg.generated
      This element is automatically generated by MyBatis Generator, do not modify.
      This element was generated on Fri Feb 24 16:09:40 CST 2023.
    -->
    <selectKey keyProperty="id" order="AFTER" resultType="java.lang.Integer">
      SELECT LAST_INSERT_ID()
    </selectKey>
    insert into units
    <trim prefix="(" suffix=")" suffixOverrides=",">
      <if test="projectnumber != null">
        ProjectNumber,
      </if>
      <if test="q != null">
        Q,
      </if>
      <if test="h != null">
        H,
      </if>
      <if test="temp != null">
        Temp,
      </if>
      <if test="viscosity != null">
        viscosity,
      </if>
      <if test="innerpressure != null">
        InnerPressure,
      </if>
      <if test="outpressure != null">
        OutPressure,
      </if>
      <if test="gas != null">
        Gas,
      </if>
      <if test="depth != null">
        Depth,
      </if>
      <if test="npsha != null">
        NPSHa,
      </if>
      <if test="npshr != null">
        NPSHr,
      </if>
      <if test="powerThis != null">
        power_this,
      </if>
      <if test="levelMoter != null">
        level_moter,
      </if>
      <if test="frequency != null">
        frequency,
      </if>
    </trim>
    <trim prefix="values (" suffix=")" suffixOverrides=",">
      <if test="projectnumber != null">
        #{projectnumber,jdbcType=VARCHAR},
      </if>
      <if test="q != null">
        #{q,jdbcType=VARCHAR},
      </if>
      <if test="h != null">
        #{h,jdbcType=VARCHAR},
      </if>
      <if test="temp != null">
        #{temp,jdbcType=VARCHAR},
      </if>
      <if test="viscosity != null">
        #{viscosity,jdbcType=VARCHAR},
      </if>
      <if test="innerpressure != null">
        #{innerpressure,jdbcType=VARCHAR},
      </if>
      <if test="outpressure != null">
        #{outpressure,jdbcType=VARCHAR},
      </if>
      <if test="gas != null">
        #{gas,jdbcType=VARCHAR},
      </if>
      <if test="depth != null">
        #{depth,jdbcType=VARCHAR},
      </if>
      <if test="npsha != null">
        #{npsha,jdbcType=VARCHAR},
      </if>
      <if test="npshr != null">
        #{npshr,jdbcType=VARCHAR},
      </if>
      <if test="powerThis != null">
        #{powerThis,jdbcType=VARCHAR},
      </if>
      <if test="levelMoter != null">
        #{levelMoter,jdbcType=VARCHAR},
      </if>
      <if test="frequency != null">
        #{frequency,jdbcType=VARCHAR},
      </if>
    </trim>
  </insert>
  <select id="countByExample" parameterType="com.t.zero.b.i.pump.db.model.auto.UnitsExample" resultType="java.lang.Long">
    <!--
      WARNING - @mbg.generated
      This element is automatically generated by MyBatis Generator, do not modify.
      This element was generated on Fri Feb 24 16:09:40 CST 2023.
    -->
    select count(*) from units
    <if test="_parameter != null">
      <include refid="Example_Where_Clause" />
    </if>
  </select>
  <update id="updateByExampleSelective" parameterType="map">
    <!--
      WARNING - @mbg.generated
      This element is automatically generated by MyBatis Generator, do not modify.
      This element was generated on Fri Feb 24 16:09:40 CST 2023.
    -->
    update units
    <set>
      <if test="record.id != null">
        id = #{record.id,jdbcType=INTEGER},
      </if>
      <if test="record.projectnumber != null">
        ProjectNumber = #{record.projectnumber,jdbcType=VARCHAR},
      </if>
      <if test="record.q != null">
        Q = #{record.q,jdbcType=VARCHAR},
      </if>
      <if test="record.h != null">
        H = #{record.h,jdbcType=VARCHAR},
      </if>
      <if test="record.temp != null">
        Temp = #{record.temp,jdbcType=VARCHAR},
      </if>
      <if test="record.viscosity != null">
        viscosity = #{record.viscosity,jdbcType=VARCHAR},
      </if>
      <if test="record.innerpressure != null">
        InnerPressure = #{record.innerpressure,jdbcType=VARCHAR},
      </if>
      <if test="record.outpressure != null">
        OutPressure = #{record.outpressure,jdbcType=VARCHAR},
      </if>
      <if test="record.gas != null">
        Gas = #{record.gas,jdbcType=VARCHAR},
      </if>
      <if test="record.depth != null">
        Depth = #{record.depth,jdbcType=VARCHAR},
      </if>
      <if test="record.npsha != null">
        NPSHa = #{record.npsha,jdbcType=VARCHAR},
      </if>
      <if test="record.npshr != null">
        NPSHr = #{record.npshr,jdbcType=VARCHAR},
      </if>
      <if test="record.powerThis != null">
        power_this = #{record.powerThis,jdbcType=VARCHAR},
      </if>
      <if test="record.levelMoter != null">
        level_moter = #{record.levelMoter,jdbcType=VARCHAR},
      </if>
      <if test="record.frequency != null">
        frequency = #{record.frequency,jdbcType=VARCHAR},
      </if>
    </set>
    <if test="_parameter != null">
      <include refid="Update_By_Example_Where_Clause" />
    </if>
  </update>
  <update id="updateByExample" parameterType="map">
    <!--
      WARNING - @mbg.generated
      This element is automatically generated by MyBatis Generator, do not modify.
      This element was generated on Fri Feb 24 16:09:40 CST 2023.
    -->
    update units
    set id = #{record.id,jdbcType=INTEGER},
      ProjectNumber = #{record.projectnumber,jdbcType=VARCHAR},
      Q = #{record.q,jdbcType=VARCHAR},
      H = #{record.h,jdbcType=VARCHAR},
      Temp = #{record.temp,jdbcType=VARCHAR},
      viscosity = #{record.viscosity,jdbcType=VARCHAR},
      InnerPressure = #{record.innerpressure,jdbcType=VARCHAR},
      OutPressure = #{record.outpressure,jdbcType=VARCHAR},
      Gas = #{record.gas,jdbcType=VARCHAR},
      Depth = #{record.depth,jdbcType=VARCHAR},
      NPSHa = #{record.npsha,jdbcType=VARCHAR},
      NPSHr = #{record.npshr,jdbcType=VARCHAR},
      power_this = #{record.powerThis,jdbcType=VARCHAR},
      level_moter = #{record.levelMoter,jdbcType=VARCHAR},
      frequency = #{record.frequency,jdbcType=VARCHAR}
    <if test="_parameter != null">
      <include refid="Update_By_Example_Where_Clause" />
    </if>
  </update>
  <update id="updateByPrimaryKeySelective" parameterType="com.t.zero.b.i.pump.db.model.auto.Units">
    <!--
      WARNING - @mbg.generated
      This element is automatically generated by MyBatis Generator, do not modify.
      This element was generated on Fri Feb 24 16:09:40 CST 2023.
    -->
    update units
    <set>
      <if test="projectnumber != null">
        ProjectNumber = #{projectnumber,jdbcType=VARCHAR},
      </if>
      <if test="q != null">
        Q = #{q,jdbcType=VARCHAR},
      </if>
      <if test="h != null">
        H = #{h,jdbcType=VARCHAR},
      </if>
      <if test="temp != null">
        Temp = #{temp,jdbcType=VARCHAR},
      </if>
      <if test="viscosity != null">
        viscosity = #{viscosity,jdbcType=VARCHAR},
      </if>
      <if test="innerpressure != null">
        InnerPressure = #{innerpressure,jdbcType=VARCHAR},
      </if>
      <if test="outpressure != null">
        OutPressure = #{outpressure,jdbcType=VARCHAR},
      </if>
      <if test="gas != null">
        Gas = #{gas,jdbcType=VARCHAR},
      </if>
      <if test="depth != null">
        Depth = #{depth,jdbcType=VARCHAR},
      </if>
      <if test="npsha != null">
        NPSHa = #{npsha,jdbcType=VARCHAR},
      </if>
      <if test="npshr != null">
        NPSHr = #{npshr,jdbcType=VARCHAR},
      </if>
      <if test="powerThis != null">
        power_this = #{powerThis,jdbcType=VARCHAR},
      </if>
      <if test="levelMoter != null">
        level_moter = #{levelMoter,jdbcType=VARCHAR},
      </if>
      <if test="frequency != null">
        frequency = #{frequency,jdbcType=VARCHAR},
      </if>
    </set>
    where id = #{id,jdbcType=INTEGER}
  </update>
  <update id="updateByPrimaryKey" parameterType="com.t.zero.b.i.pump.db.model.auto.Units">
    <!--
      WARNING - @mbg.generated
      This element is automatically generated by MyBatis Generator, do not modify.
      This element was generated on Fri Feb 24 16:09:40 CST 2023.
    -->
    update units
    set ProjectNumber = #{projectnumber,jdbcType=VARCHAR},
      Q = #{q,jdbcType=VARCHAR},
      H = #{h,jdbcType=VARCHAR},
      Temp = #{temp,jdbcType=VARCHAR},
      viscosity = #{viscosity,jdbcType=VARCHAR},
      InnerPressure = #{innerpressure,jdbcType=VARCHAR},
      OutPressure = #{outpressure,jdbcType=VARCHAR},
      Gas = #{gas,jdbcType=VARCHAR},
      Depth = #{depth,jdbcType=VARCHAR},
      NPSHa = #{npsha,jdbcType=VARCHAR},
      NPSHr = #{npshr,jdbcType=VARCHAR},
      power_this = #{powerThis,jdbcType=VARCHAR},
      level_moter = #{levelMoter,jdbcType=VARCHAR},
      frequency = #{frequency,jdbcType=VARCHAR}
    where id = #{id,jdbcType=INTEGER}
  </update>
</mapper>